splendidmoons/__init__.py
splendidmoons/__main__.py
splendidmoons/astro_moon.py
splendidmoons/calendar_consts.py
splendidmoons/calendar_day.py
splendidmoons/calendar_year.py
splendidmoons/cli.py
splendidmoons/event.py
splendidmoons/event_helpers.py
splendidmoons/half_moon.py
splendidmoons/helpers.py
splendidmoons/ical.py
splendidmoons/json_cal_day.py
splendidmoons/runner.py
splendidmoons/uposatha_moon.py
splendidmoons-1.0.2.dist-info/LICENSE.txt
splendidmoons-1.0.2.dist-info/entry_points.txt
splendidmoons-1.0.2.dist-info/WHEEL
splendidmoons-1.0.2.dist-info/METADATA
splendidmoons-1.0.2.dist-info/RECORD
