Metadata-Version: 2.1
Name: splendidmoons
Version: 1.0.2
Summary: Calculates uposatha moonday calendar data for Mahanikaya
License: MIT
Author: Gambhiro
Author-email: profound.labs@gmail.com
Requires-Python: >=3.11,<4.0
Classifier: License :: OSI Approved :: MIT License
Classifier: Programming Language :: Python :: 3
Classifier: Programming Language :: Python :: 3.11
Requires-Dist: typer (>=0.9.0,<0.10.0)
